[{"__symbolic":"module","version":3,"metadata":{"TreeController":{"__symbolic":"class","members":{"__ctor__":[{"__symbolic":"constructor","parameters":[{"__symbolic":"reference","module":"./tree-internal.component","name":"TreeInternalComponent"}]}],"select":[{"__symbolic":"method"}],"switchFoldingType":[{"__symbolic":"method"}],"expand":[{"__symbolic":"method"}],"collapse":[{"__symbolic":"method"}],"rename":[{"__symbolic":"method"}],"reloadChildren":[{"__symbolic":"method"}]}}}},{"__symbolic":"module","version":1,"metadata":{"TreeController":{"__symbolic":"class","members":{"__ctor__":[{"__symbolic":"constructor","parameters":[{"__symbolic":"reference","module":"./tree-internal.component","name":"TreeInternalComponent"}]}],"select":[{"__symbolic":"method"}],"switchFoldingType":[{"__symbolic":"method"}],"expand":[{"__symbolic":"method"}],"collapse":[{"__symbolic":"method"}],"rename":[{"__symbolic":"method"}],"reloadChildren":[{"__symbolic":"method"}]}}}}]